conformer_rl/__init__.py
conformer_rl/agents/__init__.py
conformer_rl/agents/base_ac_agent.py
conformer_rl/agents/base_ac_agent_recurrent.py
conformer_rl/agents/base_agent.py
conformer_rl/agents/base_agent_recurrent.py
conformer_rl/agents/curriculum_agents.py
conformer_rl/agents/storage.py
conformer_rl/agents/A2C/A2C_agent.py
conformer_rl/agents/A2C/A2C_recurrent_agent.py
conformer_rl/agents/A2C/__init__.py
conformer_rl/agents/PPO/PPO_agent.py
conformer_rl/agents/PPO/PPO_recurrent_agent.py
conformer_rl/agents/PPO/__init__.py
conformer_rl/analysis/__init__.py
conformer_rl/analysis/analysis.py
conformer_rl/config/__init__.py
conformer_rl/config/agent_config.py
conformer_rl/config/mol_config.py
conformer_rl/environments/__init__.py
conformer_rl/environments/conformer_env.py
conformer_rl/environments/curriculum_conformer_env.py
conformer_rl/environments/environment_wrapper.py
conformer_rl/environments/environments.py
conformer_rl/environments/simple_vec_env.py
conformer_rl/environments/environment_components/__init__.py
conformer_rl/environments/environment_components/action_mixins.py
conformer_rl/environments/environment_components/molecule_features.py
conformer_rl/environments/environment_components/obs_mixins.py
conformer_rl/environments/environment_components/reward_mixins.py
conformer_rl/logging/__init__.py
conformer_rl/logging/env_logger.py
conformer_rl/logging/train_logger.py
conformer_rl/models/RTGN.py
conformer_rl/models/RTGN_GAT.py
conformer_rl/models/RTGN_GAT_recurrent.py
conformer_rl/models/RTGN_recurrent.py
conformer_rl/models/__init__.py
conformer_rl/models/graph_components.py
conformer_rl/molecule_generation/__init__.py
conformer_rl/molecule_generation/generate_alkanes.py
conformer_rl/molecule_generation/generate_lignin.py
conformer_rl/molecule_generation/generate_molecule_config.py
conformer_rl/molecule_generation/generate_xor_gate.py
conformer_rl/utils/__init__.py
conformer_rl/utils/chem_utils.py
conformer_rl/utils/misc_utils.py
conformer_rl-1.1.0.dist-info/LICENSE
conformer_rl-1.1.0.dist-info/METADATA
conformer_rl-1.1.0.dist-info/WHEEL
conformer_rl-1.1.0.dist-info/top_level.txt
conformer_rl-1.1.0.dist-info/RECORD
