Metadata-Version: 2.1
Name: conformer-rl
Version: 1.1.0
Summary: Deep Reinforcement Library for Conformer Generation
Home-page: https://github.com/ZimmermanGroup/conformer-rl
Author: Runxuan Jiang
Author-email: runxuanj@umich.edu
License: MIT
Requires-Python: >=3.7
License-File: LICENSE
Requires-Dist: numpy
Requires-Dist: tensorflow
Requires-Dist: gym
Requires-Dist: stable-baselines3 (>=1.0)
Provides-Extra: dev
Requires-Dist: sphinx ; extra == 'dev'
Requires-Dist: sphinx-rtd-theme ; extra == 'dev'
Requires-Dist: pytest ; extra == 'dev'
Requires-Dist: coverage ; extra == 'dev'
Requires-Dist: pytest-mock ; extra == 'dev'
Provides-Extra: generate_molecules
Requires-Dist: common-wrangler (==0.3.5) ; extra == 'generate_molecules'
Requires-Dist: ligninkmc ; extra == 'generate_molecules'
Requires-Dist: stk ; extra == 'generate_molecules'
Provides-Extra: visualization
Requires-Dist: py3Dmol ; extra == 'visualization'
Requires-Dist: seaborn ; extra == 'visualization'
Requires-Dist: jupyterlab ; extra == 'visualization'
